{"frameRate":30,"isGlobal":0,"armature":[{"ik":[{"chain":1,"bone":"bone6","bendPositive":"false","name":"cvcvcvc","target":"cvcvcvc"},{"chain":1,"bone":"bone3","bendPositive":"false","name":"tytytyt","target":"tytytyt"},{"bone":"bone7","bendPositive":"false","name":"nmnmnmn","target":"nmnmnmn"},{"bone":"bone4","bendPositive":"false","name":"y6y6y6","target":"y6y6y6"}],"bone":[{"name":"root","transform":{}},{"transform":{"y":-84.18,"x":-9.2},"name":"bone","parent":"root"},{"transform":{"y":-8.67,"x":-39.48},"name":"nmnmnmn","parent":"root"},{"transform":{"y":-16.73,"x":-37.6},"name":"cvcvcvc","parent":"root"},{"transform":{"y":-8.62,"x":61.11},"name":"y6y6y6","parent":"root"},{"transform":{"y":-8.19,"x":-1.06},"name":"bone24","parent":"root"},{"transform":{"y":-17.32,"x":57.61},"name":"tytytyt","parent":"root"},{"length":48,"transform":{"y":1.02,"skX":133.01,"skY":133.01,"x":-5.75},"parent":"bone","name":"bone5"},{"length":47,"transform":{"y":0.15,"skX":48.22,"skY":48.22,"x":11.93},"parent":"bone","name":"bone2"},{"length":7,"transform":{"y":-2.18,"skX":-82.12,"skY":-82.12,"x":-0.5},"parent":"bone","name":"bone8"},{"transform":{"y":2.17,"x":-0.56},"name":"bone20","parent":"bone"},{"length":23,"transform":{"y":1.5,"skX":78.98,"skY":78.98,"x":0.7},"parent":"bone20","name":"bone22"},{"length":38,"transform":{"y":-0.12,"skX":4.96,"skY":4.96,"x":47.9},"parent":"bone2","name":"bone3"},{"length":32,"transform":{"skX":-61.83,"skY":-61.83,"x":48.5},"parent":"bone5","name":"bone6"},{"length":12,"transform":{"skX":-22.99,"skY":-22.99,"x":7.61},"parent":"bone8","name":"bone9"},{"length":19,"transform":{"y":2.2,"skX":131.61,"skY":131.61,"x":-10.2},"parent":"bone20","name":"bone21"},{"length":27,"transform":{"y":-5.74,"skX":7.05,"skY":7.05,"x":13.3},"parent":"bone20","name":"bone23"},{"length":7,"transform":{"y":0.02,"skX":31.53,"skY":31.53,"x":32.64},"parent":"bone6","name":"bone7"},{"length":8,"transform":{"y":0.44,"skX":13.76,"skY":13.76,"x":38.88},"parent":"bone3","name":"bone4"},{"length":25,"transform":{"skX":-2.42,"skY":-2.42,"x":12.02},"parent":"bone9","name":"bone10"},{"length":31,"transform":{"y":-9.98,"skX":-133.84,"skY":-133.84,"x":20.63},"parent":"bone10","name":"bone17"},{"length":32,"transform":{"y":18.15,"skX":112.94,"skY":112.94,"x":25.48},"parent":"bone10","name":"bone14"},{"length":28,"transform":{"skX":-22.72,"skY":-22.72,"x":25.42},"parent":"bone10","name":"bone11"},{"length":33,"transform":{"y":0.5,"skX":62.78,"skY":62.78,"x":32.05},"parent":"bone17","name":"bone18"},{"length":21,"transform":{"y":11.27,"skX":72.24,"skY":72.24,"x":21.39},"parent":"bone11","name":"bone12"},{"length":12,"transform":{"y":-4.15,"skX":42.49,"skY":42.49,"x":30.34},"parent":"bone11","name":"bone13"},{"length":29,"transform":{"y":1.12,"skX":43.81,"skY":43.81,"x":31.87},"parent":"bone14","name":"bone15"},{"length":74,"transform":{"y":10.45,"skX":-1.46,"skY":-1.46,"x":40.32},"parent":"bone18","name":"bone19"},{"length":16,"transform":{"skX":24.17,"skY":24.17,"x":29.05},"parent":"bone15","name":"bone16"},{"length":82,"transform":{"y":-3.42,"skX":55.37,"skY":55.37,"x":38.66},"parent":"bone18","name":"bone25"}],"type":"Armature","frameRate":30,"animation":[{"ik":[],"bone":[{"frame":[{"curve":[0.258,0,1,0],"transform":{},"duration":10},{"curve":[0.25,0,0.754,1],"transform":{"x":9.9},"duration":5},{"curve":[0.25,0,0,1],"transform":{"y":1.82,"x":20.58},"duration":5},{"curve":[0.25,0,0.75,1],"transform":{"y":11.5,"x":-0.99},"duration":4},{"curve":[0.25,0,0.75,1],"transform":{"y":11.92,"x":-0.99},"duration":11},{"transform":{},"duration":0}],"name":"bone"},{"frame":[{"curve":[0.258,0,1,0],"transform":{"skX":3.61,"skY":3.61},"duration":10},{"curve":[0.25,0,0.754,1],"transform":{"skX":27,"skY":27},"duration":5},{"curve":[0.516,0,0,1],"transform":{"skX":34.81,"skY":34.81},"duration":5},{"transform":{"skX":16.7,"skY":16.7},"duration":4},{"curve":[0.093,0.33,0.147,1],"transform":{"skX":16.7,"skY":16.7},"duration":11},{"transform":{"skX":3.61,"skY":3.61},"duration":0}],"name":"bone2"},{"frame":[{"curve":[0.258,0,1,0],"transform":{"skX":-7.62,"skY":-7.62},"duration":10},{"curve":[0.25,0,0.754,1],"transform":{"skX":-48.14,"skY":-48.14},"duration":5},{"curve":[0.516,0,0,1],"transform":{"skX":-61.2,"skY":-61.2},"duration":5},{"transform":{"skX":-46.92,"skY":-46.92},"duration":4},{"curve":[0.093,0.33,0.147,1],"transform":{"skX":-46.92,"skY":-46.92},"duration":11},{"transform":{"skX":-7.62,"skY":-7.62},"duration":0}],"name":"bone3"},{"frame":[{"curve":[0.258,0,1,0],"transform":{"skX":3.25,"skY":3.25},"duration":10},{"curve":[0.25,0,0.754,1],"transform":{"skX":21.4,"skY":21.4},"duration":5},{"curve":[0.516,0,0,1],"transform":{"skX":26.99,"skY":26.99},"duration":5},{"transform":{"skX":31.08,"skY":31.08},"duration":4},{"curve":[0.093,0.33,0.147,1],"transform":{"skX":31.08,"skY":31.08},"duration":11},{"transform":{"skX":3.25,"skY":3.25},"duration":0}],"name":"bone4"},{"frame":[{"curve":[0.258,0,1,0],"transform":{"skX":-0.07,"skY":-0.07},"duration":10},{"curve":[0.25,0,0.754,1],"transform":{"skX":2.68,"skY":2.68},"duration":5},{"curve":[0.516,0,0,1],"transform":{"skX":5.72,"skY":5.72},"duration":5},{"transform":{"skX":8.89,"skY":8.89},"duration":4},{"curve":[0.093,0.33,0.147,1],"transform":{"skX":8.89,"skY":8.89},"duration":11},{"transform":{"skX":-0.07,"skY":-0.07},"duration":0}],"name":"bone5"},{"frame":[{"curve":[0.258,0,1,0],"transform":{"skX":0.32,"skY":0.32},"duration":10},{"curve":[0.25,0,0.754,1],"transform":{"skX":12.35,"skY":12.35},"duration":5},{"curve":[0.516,0,0,1],"transform":{"skX":14.46,"skY":14.46},"duration":5},{"transform":{"skX":-20.47,"skY":-20.47},"duration":4},{"curve":[0.093,0.33,0.147,1],"transform":{"skX":-20.47,"skY":-20.47},"duration":11},{"transform":{"skX":0.32,"skY":0.32},"duration":0}],"name":"bone6"},{"frame":[{"curve":[0.258,0,1,0],"transform":{"skX":0.05,"skY":0.05},"duration":10},{"curve":[0.25,0,0.754,1],"transform":{"skX":-14.77,"skY":-14.77},"duration":5},{"curve":[0.516,0,0,1],"transform":{"skX":-19.93,"skY":-19.93},"duration":5},{"transform":{"skX":11.91,"skY":11.91},"duration":4},{"curve":[0.093,0.33,0.147,1],"transform":{"skX":11.91,"skY":11.91},"duration":11},{"transform":{"skX":0.05,"skY":0.05},"duration":0}],"name":"bone7"},{"frame":[{"curve":[0.258,0,1,0],"transform":{},"duration":10},{"curve":[0.25,0,0.754,1],"transform":{"skX":7.57,"skY":7.57},"duration":5},{"curve":[0.25,0,0,1],"transform":{"skX":4.29,"skY":4.29},"duration":5},{"transform":{"skX":-19.59,"skY":-19.59},"duration":4},{"curve":[0.25,0,0.75,1],"transform":{"skX":-19.59,"skY":-19.59},"duration":11},{"transform":{},"duration":0}],"name":"bone8"},{"frame":[{"curve":[0.258,0,1,0],"transform":{},"duration":10},{"transform":{"skX":25.22,"skY":25.22},"duration":5},{"curve":[0.25,0,0,1],"transform":{"skX":25.22,"skY":25.22},"duration":5},{"transform":{"skX":22.6,"skY":22.6},"duration":4},{"curve":[0.25,0,0.75,1],"transform":{"skX":22.6,"skY":22.6},"duration":11},{"transform":{},"duration":0}],"name":"bone9"},{"frame":[{"curve":[0.258,0,1,0],"transform":{},"duration":10},{"curve":[0.25,0,0.754,1],"transform":{"skX":-43.93,"skY":-43.93},"duration":5},{"curve":[0.25,0,0,1],"transform":{"skX":-25.23,"skY":-25.23},"duration":5},{"transform":{"skX":-7.46,"skY":-7.46},"duration":4},{"curve":[0.25,0,0.75,1],"transform":{"skX":-7.46,"skY":-7.46},"duration":11},{"transform":{},"duration":0}],"name":"bone10"},{"frame":[{"curve":[0.258,0,1,0],"transform":{"skX":0.14,"skY":0.14},"duration":10},{"curve":[0.25,0,0.754,1],"transform":{"skX":10.62,"skY":10.62},"duration":5},{"curve":[0.25,0,0,1],"transform":{"skX":38.7,"skY":38.7},"duration":5},{"transform":{"skX":-9.9,"skY":-9.9},"duration":4},{"curve":[0.25,0,0.75,1],"transform":{"skX":-9.9,"skY":-9.9},"duration":11},{"transform":{"skX":0.14,"skY":0.14},"duration":0}],"name":"bone14"},{"frame":[{"curve":[0.258,0,1,0],"transform":{"skX":0.88,"skY":0.88},"duration":10},{"curve":[0.25,0,0.754,1],"transform":{"skX":4.14,"skY":4.14},"duration":5},{"curve":[0.25,0,0,1],"transform":{"skX":17.16,"skY":17.16},"duration":5},{"transform":{"skX":-17.84,"skY":-17.84},"duration":4},{"curve":[0.25,0,0.75,1],"transform":{"skX":-17.84,"skY":-17.84},"duration":11},{"transform":{"skX":0.88,"skY":0.88},"duration":0}],"name":"bone15"},{"frame":[{"curve":[0.258,0,1,0],"transform":{"skX":0.42,"skY":0.42},"duration":10},{"curve":[0.25,0,0.754,1],"transform":{"skX":0.41,"skY":0.41},"duration":5},{"curve":[0.25,0,0,1],"transform":{"skX":-97.12,"skY":-97.12},"duration":5},{"transform":{"skX":32.59,"skY":32.59},"duration":4},{"curve":[0.25,0,0.75,1],"transform":{"skX":32.59,"skY":32.59},"duration":11},{"transform":{"skX":0.42,"skY":0.42},"duration":0}],"name":"bone17"},{"frame":[{"curve":[0.258,0,1,0],"transform":{"skX":-1.06,"skY":-1.06},"duration":10},{"curve":[0.25,0,0.754,1],"transform":{"skX":15.13,"skY":15.13},"duration":5},{"curve":[0.25,0,0,1],"transform":{"skX":54.86,"skY":54.86},"duration":5},{"transform":{"skX":-37.86,"skY":-37.86},"duration":4},{"curve":[0.25,0,0.75,1],"transform":{"skX":-37.86,"skY":-37.86},"duration":11},{"transform":{"skX":-1.06,"skY":-1.06},"duration":0}],"name":"bone18"},{"frame":[{"curve":[0.129,0,1,0.5],"transform":{},"duration":10},{"curve":[0.25,0,0.754,1],"transform":{"scX":1.1},"duration":5},{"curve":[0.383,0,0,1],"transform":{"scX":1.16,"x":9.31},"duration":5},{"transform":{"scX":1.35,"x":4.03},"duration":4},{"curve":[0.1715,0.165,0.4485,1],"transform":{"scX":1.35,"x":4.03},"duration":11},{"transform":{},"duration":0}],"name":"bone24"},{"frame":[{"curve":[0.25,0,1,0],"transform":{},"duration":10},{"curve":[0.25,0,0.754,1],"transform":{"skX":4.77,"skY":4.77},"duration":5},{"curve":[0.383,0,0,1],"transform":{},"duration":5},{"transform":{"y":-0.18,"skX":-34.21,"skY":-34.21,"x":-7.13},"duration":4},{"curve":[0.0465,0.165,0.5735,1],"transform":{"y":-0.18,"skX":-34.21,"skY":-34.21,"x":-7.13},"duration":11},{"transform":{},"duration":0}],"name":"bone25"},{"frame":[{"transform":{},"duration":35}],"name":"root"},{"frame":[{"transform":{},"duration":35}],"name":"nmnmnmn"},{"frame":[{"transform":{},"duration":35}],"name":"cvcvcvc"},{"frame":[{"transform":{},"duration":35}],"name":"y6y6y6"},{"frame":[{"transform":{},"duration":35}],"name":"tytytyt"},{"frame":[{"transform":{},"duration":35}],"name":"bone20"},{"frame":[{"transform":{},"duration":35}],"name":"bone22"},{"frame":[{"transform":{},"duration":35}],"name":"bone21"},{"frame":[{"transform":{},"duration":35}],"name":"bone23"},{"frame":[{"transform":{},"duration":35}],"name":"bone11"},{"frame":[{"transform":{},"duration":35}],"name":"bone12"},{"frame":[{"transform":{},"duration":35}],"name":"bone13"},{"frame":[{"transform":{},"duration":35}],"name":"bone19"},{"frame":[{"transform":{},"duration":35}],"name":"bone16"}],"slot":[],"ffd":[{"frame":[{"offset":0,"curve":[0.238,0,1,0],"vertices":[],"duration":15},{"offset":8,"curve":[0.25,0,0,1],"vertices":[-5.74,-1.19],"duration":20},{"offset":0,"tweenEasing":null,"vertices":[],"duration":0}],"slot":"Layer 149","scale":1,"offset":0,"skin":"","name":"Layer 149"}],"frame":[],"name":"Attack A","duration":35},{"ik":[],"bone":[{"frame":[{"curve":[0.265,0,0,1],"transform":{},"duration":10},{"curve":[0.25,0,0.75,1],"transform":{"y":0.4,"x":14.34},"duration":20},{"transform":{},"duration":0}],"name":"bone"},{"frame":[{"curve":[0.265,0,0,1],"transform":{"skX":3.61,"skY":3.61},"duration":10},{"curve":[0.25,0,0.75,1],"transform":{"skX":33.52,"skY":33.52},"duration":20},{"transform":{"skX":3.61,"skY":3.61},"duration":0}],"name":"bone2"},{"frame":[{"curve":[0.265,0,0,1],"transform":{"skX":-7.62,"skY":-7.62},"duration":10},{"curve":[0.25,0,0.75,1],"transform":{"skX":-57.27,"skY":-57.27},"duration":20},{"transform":{"skX":-7.62,"skY":-7.62},"duration":0}],"name":"bone3"},{"frame":[{"curve":[0.265,0,0,1],"transform":{"skX":3.25,"skY":3.25},"duration":10},{"curve":[0.25,0,0.75,1],"transform":{"skX":24.18,"skY":24.18},"duration":20},{"transform":{"skX":3.25,"skY":3.25},"duration":0}],"name":"bone4"},{"frame":[{"curve":[0.265,0,0,1],"transform":{"skX":-0.07,"skY":-0.07},"duration":10},{"curve":[0.25,0,0.75,1],"transform":{"skX":3.37,"skY":3.37},"duration":20},{"transform":{"skX":-0.07,"skY":-0.07},"duration":0}],"name":"bone5"},{"frame":[{"curve":[0.265,0,0,1],"transform":{"skX":0.32,"skY":0.32},"duration":10},{"curve":[0.25,0,0.75,1],"transform":{"skX":18.75,"skY":18.75},"duration":20},{"transform":{"skX":0.32,"skY":0.32},"duration":0}],"name":"bone6"},{"frame":[{"curve":[0.265,0,0,1],"transform":{"skX":0.05,"skY":0.05},"duration":10},{"curve":[0.25,0,0.75,1],"transform":{"skX":-21.88,"skY":-21.88},"duration":20},{"transform":{"skX":0.05,"skY":0.05},"duration":0}],"name":"bone7"},{"frame":[{"curve":[0.265,0,0,1],"transform":{},"duration":10},{"curve":[0.25,0,0.75,1],"transform":{"skX":12.17,"skY":12.17},"duration":20},{"transform":{},"duration":0}],"name":"bone10"},{"frame":[{"curve":[0.265,0,0,1],"transform":{"skX":0.14,"skY":0.14},"duration":10},{"curve":[0.25,0,0.75,1],"transform":{"skX":-10.95,"skY":-10.95},"duration":20},{"transform":{"skX":0.14,"skY":0.14},"duration":0}],"name":"bone14"},{"frame":[{"transform":{"skX":0.88,"skY":0.88},"duration":30}],"name":"bone15"},{"frame":[{"curve":[0.265,0,0,1],"transform":{"skX":0.42,"skY":0.42},"duration":10},{"curve":[0.25,0,0.75,1],"transform":{"skX":-30.99,"skY":-30.99},"duration":20},{"transform":{"skX":0.42,"skY":0.42},"duration":0}],"name":"bone17"},{"frame":[{"transform":{"skX":-1.06,"skY":-1.06},"duration":30}],"name":"bone18"},{"frame":[{"curve":[0.265,0,0,1],"transform":{},"duration":10},{"curve":[0.25,0,0.75,1],"transform":{"skX":21.49,"skY":21.49},"duration":20},{"transform":{},"duration":0}],"name":"bone21"},{"frame":[{"curve":[0.265,0,0,1],"transform":{},"duration":10},{"curve":[0.25,0,0.75,1],"transform":{"skX":31.56,"skY":31.56},"duration":20},{"transform":{},"duration":0}],"name":"bone22"},{"frame":[{"curve":[0.265,0,0,1],"transform":{},"duration":10},{"curve":[0.25,0,0.75,1],"transform":{"skX":21.83,"skY":21.83},"duration":20},{"transform":{},"duration":0}],"name":"bone23"},{"frame":[{"curve":[0.265,0,0,1],"transform":{},"duration":10},{"curve":[0.25,0,0.75,1],"transform":{"scX":1.14},"duration":20},{"transform":{},"duration":0}],"name":"bone24"},{"frame":[{"transform":{},"duration":30}],"name":"root"},{"frame":[{"transform":{},"duration":30}],"name":"nmnmnmn"},{"frame":[{"transform":{},"duration":30}],"name":"cvcvcvc"},{"frame":[{"transform":{},"duration":30}],"name":"y6y6y6"},{"frame":[{"transform":{},"duration":30}],"name":"tytytyt"},{"frame":[{"transform":{},"duration":30}],"name":"bone8"},{"frame":[{"transform":{},"duration":30}],"name":"bone20"},{"frame":[{"transform":{},"duration":30}],"name":"bone9"},{"frame":[{"transform":{},"duration":30}],"name":"bone11"},{"frame":[{"transform":{},"duration":30}],"name":"bone12"},{"frame":[{"transform":{},"duration":30}],"name":"bone13"},{"frame":[{"transform":{},"duration":30}],"name":"bone19"},{"frame":[{"transform":{},"duration":30}],"name":"bone16"},{"frame":[{"transform":{},"duration":30}],"name":"bone25"}],"slot":[],"ffd":[{"frame":[{"offset":0,"curve":[0.265,0,0,1],"vertices":[],"duration":10},{"offset":8,"curve":[0.25,0,0.75,1],"vertices":[-4.98,-0.41],"duration":20},{"offset":0,"tweenEasing":null,"vertices":[],"duration":0}],"slot":"Layer 149","scale":1,"offset":0,"skin":"","name":"Layer 149"}],"frame":[],"name":"Damage","duration":30},{"ik":[],"bone":[{"frame":[{"curve":[0.25,0,0.75,1],"transform":{},"duration":30},{"curve":[0.25,0,0.75,1],"transform":{"y":7.4,"x":8.98},"duration":30},{"transform":{},"duration":0}],"name":"bone"},{"frame":[{"transform":{"skX":3.61,"skY":3.61},"duration":60}],"name":"bone2"},{"frame":[{"transform":{"skX":-7.62,"skY":-7.62},"duration":60}],"name":"bone3"},{"frame":[{"transform":{"skX":3.25,"skY":3.25},"duration":60}],"name":"bone4"},{"frame":[{"transform":{"skX":-0.07,"skY":-0.07},"duration":60}],"name":"bone5"},{"frame":[{"transform":{"skX":0.32,"skY":0.32},"duration":60}],"name":"bone6"},{"frame":[{"transform":{"skX":0.05,"skY":0.05},"duration":60}],"name":"bone7"},{"frame":[{"curve":[0.25,0,0.75,1],"transform":{},"duration":36},{"curve":[0.25,0,0.75,1],"transform":{"skX":8.48,"skY":8.48},"duration":24},{"transform":{},"duration":0}],"name":"bone12"},{"frame":[{"curve":[0.25,0,0.75,1],"transform":{},"duration":27},{"curve":[0.25,0,0.75,1],"transform":{"skX":9.43,"skY":9.43},"duration":33},{"transform":{},"duration":0}],"name":"bone13"},{"frame":[{"curve":[0.25,0,0.75,1],"transform":{"skX":0.14,"skY":0.14},"duration":24},{"curve":[0.25,0,0.75,1],"transform":{"skX":-7.25,"skY":-7.25},"duration":36},{"transform":{"skX":0.14,"skY":0.14},"duration":0}],"name":"bone14"},{"frame":[{"curve":[0.25,0,0.75,1],"transform":{"skX":0.88,"skY":0.88},"duration":29},{"curve":[0.25,0,0.75,1],"transform":{"skX":-8.64,"skY":-8.64},"duration":31},{"transform":{"skX":0.88,"skY":0.88},"duration":0}],"name":"bone15"},{"frame":[{"curve":[0.25,0,0.75,1],"transform":{"skX":0.42,"skY":0.42},"duration":25},{"curve":[0.25,0,0.75,1],"transform":{"skX":-9.55,"skY":-9.55},"duration":35},{"transform":{"skX":0.42,"skY":0.42},"duration":0}],"name":"bone17"},{"frame":[{"curve":[0.25,0,0.75,1],"transform":{"skX":-1.06,"skY":-1.06},"duration":30},{"curve":[0.25,0,0.75,1],"transform":{"skX":-7.14,"skY":-7.14},"duration":30},{"transform":{"skX":-1.06,"skY":-1.06},"duration":0}],"name":"bone18"},{"frame":[{"curve":[0.25,0,0.75,1],"transform":{},"duration":21},{"curve":[0.25,0,0.75,1],"transform":{"skX":15.17,"skY":15.17},"duration":39},{"transform":{},"duration":0}],"name":"bone21"},{"frame":[{"curve":[0.25,0,0.75,1],"transform":{},"duration":25},{"curve":[0.25,0,0.75,1],"transform":{"skX":12.89,"skY":12.89},"duration":35},{"transform":{},"duration":0}],"name":"bone22"},{"frame":[{"curve":[0.25,0,0.75,1],"transform":{},"duration":34},{"curve":[0.25,0,0.75,1],"transform":{"skX":-12.7,"skY":-12.7},"duration":26},{"transform":{},"duration":0}],"name":"bone23"},{"frame":[{"curve":[0.25,0,0.75,1],"transform":{},"duration":30},{"curve":[0.25,0,0.75,1],"transform":{"scX":1.08},"duration":30},{"transform":{},"duration":0}],"name":"bone24"},{"frame":[{"transform":{},"duration":60}],"name":"root"},{"frame":[{"transform":{},"duration":60}],"name":"nmnmnmn"},{"frame":[{"transform":{},"duration":60}],"name":"cvcvcvc"},{"frame":[{"transform":{},"duration":60}],"name":"y6y6y6"},{"frame":[{"transform":{},"duration":60}],"name":"tytytyt"},{"frame":[{"transform":{},"duration":60}],"name":"bone8"},{"frame":[{"transform":{},"duration":60}],"name":"bone20"},{"frame":[{"transform":{},"duration":60}],"name":"bone9"},{"frame":[{"transform":{},"duration":60}],"name":"bone10"},{"frame":[{"transform":{},"duration":60}],"name":"bone11"},{"frame":[{"transform":{},"duration":60}],"name":"bone19"},{"frame":[{"transform":{},"duration":60}],"name":"bone16"},{"frame":[{"transform":{},"duration":60}],"name":"bone25"}],"slot":[],"ffd":[{"frame":[{"offset":0,"curve":[0.25,0,0.75,1],"vertices":[],"duration":30},{"offset":8,"curve":[0.25,0,0.75,1],"vertices":[-5.68,-3.18,-3.44,-1.46],"duration":30},{"offset":0,"tweenEasing":null,"vertices":[],"duration":0}],"slot":"Layer 149","scale":1,"offset":0,"skin":"","name":"Layer 149"}],"frame":[],"name":"Idle","duration":60}],"defaultActions":[{"gotoAndPlay":"Attack A"}],"aabb":{"width":215.98870339797276,"y":-180.36416406818185,"height":181.23416406818185,"x":-112.31870339797277},"slot":[{"name":"Ellipse 1","parent":"bone24","color":{}},{"z":1,"name":"Layer 11 copy","parent":"bone6","color":{}},{"z":2,"name":"Layer 145","parent":"bone7","color":{}},{"z":3,"name":"Layer 146","parent":"bone5","color":{}},{"z":4,"name":"Layer 147","parent":"bone3","color":{}},{"z":5,"name":"Layer 148","parent":"bone4","color":{}},{"z":6,"name":"Layer 149","parent":"bone2","color":{}},{"z":7,"name":"Layer 150","parent":"bone17","color":{}},{"z":8,"name":"Layer 151","parent":"bone18","color":{}},{"z":9,"displayIndex":-1,"name":"Group 3","parent":"bone25","color":{}},{"z":10,"displayIndex":-1,"name":"Group 2","parent":"bone25","color":{}},{"z":11,"name":"Layer 152","parent":"bone25","color":{}},{"z":12,"name":"Layer 153","parent":"bone25","color":{}},{"z":13,"name":"Layer 154","parent":"root","color":{}},{"z":14,"name":"Layer 7 copy","parent":"bone14","color":{}},{"z":15,"name":"Layer 155","parent":"root","color":{}},{"z":16,"name":"Layer 156","parent":"root","color":{}}],"name":"DaggerGoblin","skin":[{"slot":[{"display":[{"path":"Group 3","type":"image","name":"Group 3","transform":{"y":2.07,"skX":123.22,"skY":123.22,"x":28.3}}],"name":"Group 3"},{"display":[{"vertices":[23.67,-122.08,28.23,-110.99,35.94,-111.99,40.26,-109.53,38.48,-108.98,38.94,-103.52,37.4,-98.36,45.26,-88.89,47.03,-95.2,48.95,-87.59,53.42,-84.13,55.19,-88.35,61.89,-97.36,63.67,-104.14,63.67,-110.69,58.42,-110.76,54.8,-117.22,46.34,-140.13,25.54,-140.12,23.67,-133.4,37.78,-131.47,50.1,-110.68,53.68,-105.44,44.58,-104.75],"edges":[0,1,1,2,2,3,3,4,4,5,5,6,6,7,7,8,8,9,9,10,10,11,11,12,12,13,13,14,14,15,15,16,16,17,17,18,18,19,19,0],"path":"Layer 155","uvs":[0,0.32229,0.11417,0.52028,0.30667,0.50241,0.41447,0.54641,0.3702,0.55603,0.38175,0.65366,0.34325,0.74578,0.53959,0.91491,0.58387,0.80216,0.63199,0.93828,0.74364,1,0.78792,0.92453,0.95539,0.76366,1,0.64266,1,0.52578,0.86877,0.52441,0.77829,0.40891,0.56654,0,0.0468,0,0,0.12016,0.35287,0.15454,0.66087,0.52578,0.75023,0.61942,0.52253,0.63174],"bonePose":[26,0.6531563230639635,0.7572230963471487,-0.7572230963471487,0.6531563230639635,29.464868138156813,-131.1463611912505,28,0.2858556218950479,0.9582726978428402,-0.9582726978428402,0.2858556218950479,48.439059323164955,-109.14903024236582],"triangles":[22,12,13,15,22,13,14,15,13,8,11,12,22,8,12,17,20,16,16,21,15,21,22,15,23,8,22,2,3,16,20,2,16,9,10,11,8,9,11,3,21,16,21,23,22,3,23,21,5,6,23,6,7,8,23,6,8,18,20,17,3,5,23,0,2,20,4,5,3,0,1,2,18,19,20,19,0,20],"type":"mesh","transform":{},"slotPose":[1,0,0,1,0,0],"userEdges":[],"width":40,"height":56,"name":"Layer 155","weights":[1,26,1,1,26,1,2,26,0.9942,28,0.0058,2,26,0.79733,28,0.20267,2,26,0.68449,28,0.31551,2,26,0.30735,28,0.69265,2,26,0.10299,28,0.89701,1,28,1,2,26,0.00426,28,0.99574,1,28,1,1,28,1,1,28,1,1,28,1,2,26,0.0011,28,0.9989,2,26,0.02559,28,0.97441,2,26,0.16893,28,0.83107,2,26,0.84261,28,0.15739,1,26,1,1,26,1,1,26,1,1,26,1,2,26,0.66033,28,0.33967,2,26,0.01265,28,0.98735,2,26,0.25533,28,0.74467]}],"name":"Layer 155"},{"display":[{"path":"Layer 151","type":"image","name":"Layer 151","transform":{"y":-1.03,"skX":179.23,"skY":179.23,"x":19.29}}],"name":"Layer 151"},{"display":[{"path":"Ellipse 1","type":"image","name":"Ellipse 1","transform":{"y":-0.94,"x":0.73}}],"name":"Ellipse 1"},{"display":[{"width":53,"triangles":[7,13,6,5,3,4,6,14,5,14,3,5,13,14,6,2,3,14,13,2,14,12,13,7,13,1,2,12,1,13,8,12,7,0,1,12,9,12,8,9,10,12,10,11,12,11,0,12],"type":"mesh","vertices":[-0.74,12.57,10.64,16.52,42.12,11.18,48.77,4.51,59.75,-5.53,53.05,-9.67,44.75,-12.2,4.64,-16.11,-4.32,-13.58,-11.8,-4.79,-11.92,1.7,-7.3,6.99,-0.24,-0.48,23.13,0.16,44.26,-2.24],"transform":{},"edges":[0,1,1,2,2,3,3,4,4,5,5,6,6,7,7,8,8,9,9,10,10,11,11,0],"userEdges":[],"path":"Layer 149","uvs":[0,0.3645,0.08248,0.57235,0.54439,0.95201,0.72144,0.96564,1,1,0.97748,0.85575,0.91238,0.70838,0.47776,0.0959,0.33195,0,0.11411,0,0.0195,0.07631,0,0.20494,0.19362,0.21479,0.47027,0.55197,0.76331,0.82117],"height":54,"name":"Layer 149"}],"name":"Layer 149"},{"display":[{"path":"Layer 153","type":"image","name":"Layer 153","transform":{"y":0.13,"skX":123.87,"skY":123.87,"x":1.27}}],"name":"Layer 153"},{"display":[{"path":"Layer 152","type":"image","name":"Layer 152","transform":{"y":2.58,"skX":123.22,"skY":123.22,"x":17.21}}],"name":"Layer 152"},{"display":[{"width":47,"triangles":[4,7,3,7,0,3,1,2,3,0,1,3,5,7,4,6,7,5],"type":"mesh","vertices":[33.99,3.93,38.46,3.31,43,-2.34,36.87,-10.25,11.56,-19.48,-1.19,-16.61,-7.88,-8.22,14.19,2.71],"transform":{},"edges":[6,7,7,0,0,1,1,2,2,3,3,4,4,5,5,6],"userEdges":[],"path":"Layer 147","uvs":[0.59714,0.7902,0.66595,0.84827,0.82025,0.85009,0.87237,0.67042,0.69514,0.19585,0.47982,0.04283,0.2515,0.04101,0.35784,0.48746],"height":54,"name":"Layer 147"}],"name":"Layer 147"},{"display":[{"path":"Group 2","type":"image","name":"Group 2","transform":{"y":-8.49,"skX":123.22,"skY":123.22,"x":30.43}}],"name":"Group 2"},{"display":[{"vertices":[-28.92,-99.32,-34.66,-107.78,-34.87,-119.33,-29.9,-128.64,-37.6,-124.58,-38.72,-124.86,-43.27,-115.2,-48.24,-123.53,-48.32,-132.63,-46.35,-132.77,-45.93,-134.52,-48.32,-137.81,-46.63,-140.68,-46.08,-149.33,-46.98,-155.91,-41.45,-166.91,-38.51,-154.23,-32.42,-157.8,-28.78,-159.35,-21.64,-166.73,-12.61,-173.92,-9.18,-173.91,-14.71,-160.15,-13.24,-157.2,-13.1,-153.21,-18.07,-151.32,-18.21,-149.29,-15.48,-148.03,-13.1,-145.37,-1.2,-145.44,9.02,-135.58,8.23,-122.63,6.55,-108.7,6.62,-99.95,15.58,-91.48,15.02,-84.41,13.27,-76.29,1.76,-69.18,-9.44,-66.02,-19.73,-67.36,-26.52,-74.35,-25.47,-84.93,-19.94,-92.21,-23.02,-97.18,-25.12,-119.25,-21.05,-102.87,-25.37,-111.78,-3.76,-117.54,-5.59,-123.83,-7.17,-134.05,-15.68,-133.78,-21.44,-135.35,-35.07,-139.55,-25.9,-149.11,-42.14,-128.94,-15.03,-92.52,-2.32,-101.95,1.62,-88.85,-14.37,-81.78,-14.5,-113.61,-29.43,-108.37,0.59,-133.55],"edges":[8,7,7,6,6,5,5,4,4,3,3,2,2,1,1,0,0,43,43,42,42,41,41,40,40,39,39,38,38,37,37,36,36,35,35,34,34,33,33,32,32,31,31,30,30,29,29,28,28,27,27,26,26,25,25,24,24,23,23,22,22,21,21,20,20,19,19,18,18,17,17,16,16,15,15,14,14,13,13,12,12,11,11,10,10,9,9,8],"path":"Layer 154","uvs":[0.30316,0.69266,0.21347,0.61229,0.21019,0.50535,0.28785,0.41914,0.16753,0.45674,0.15003,0.45414,0.07894,0.54359,0.00128,0.46646,0,0.3822,0.03082,0.3809,0.03738,0.3647,0,0.33424,0.02644,0.30766,0.03519,0.2276,0.02097,0.16668,0.10738,0.06485,0.15332,0.18217,0.24847,0.14911,0.30535,0.13485,0.41691,0.06655,0.558,0,0.61159,0,0.52519,0.12747,0.54816,0.15469,0.55034,0.19164,0.47269,0.20914,0.4705,0.22793,0.51316,0.2396,0.55034,0.26423,0.73628,0.26358,0.89597,0.35497,0.88358,0.47482,0.85733,0.60381,0.85843,0.68482,0.99843,0.76325,0.98968,0.82871,0.96233,0.9039,0.78251,0.96975,0.60751,0.99892,0.44673,0.9866,0.34064,0.92179,0.3822,0.82586,0.44345,0.75651,0.39532,0.71049,0.36264,0.50616,0.4261,0.65778,0.35855,0.57576,0.69628,0.52192,0.66763,0.4637,0.64306,0.36909,0.51002,0.37152,0.41996,0.35696,0.20708,0.31815,0.35036,0.2296,0.09655,0.4164,0.52025,0.7536,0.7188,0.66627,0.7802,0.78756,0.53049,0.85306,0.52844,0.55831,0.2951,0.60735,0.76415,0.37371],"bonePose":[9,0.13709878464245415,-0.9905573800893928,0.9905573800893928,0.13709878464245415,-9.7,-86.36000000000001,14,-0.26067301143654964,-0.965427149560546,0.965427149560546,-0.26067301143654964,-8.656678248870923,-93.8981416624803,19,-0.30120512328903476,-0.95355937083353,0.95355937083353,-0.30120512328903476,-11.78996784633825,-105.50257600019806,22,-0.6461239796429639,-0.7632324697825289,0.7632324697825289,-0.6461239796429639,-19.446602080345514,-129.7420552067864,25,0.0390854167953536,-0.9992358731520468,0.9992358731520468,0.0390854167953536,-42.21741837231053,-150.21711382447003,24,0.5297712438478924,-0.8481405715987516,0.8481405715987516,0.5297712438478924,-24.66556407045941,-153.3494149860109],"triangles":[57,35,34,33,57,34,57,36,35,57,37,36,29,61,30,61,48,31,48,47,31,47,32,31,30,61,31,58,37,57,47,56,32,32,56,33,56,57,33,47,59,56,29,49,61,49,48,61,58,38,37,56,55,57,55,58,57,28,49,29,59,45,56,45,55,56,20,22,21,48,59,47,58,39,38,28,50,49,49,50,48,50,59,48,50,44,59,19,22,20,51,44,50,43,42,55,45,43,55,40,39,58,55,42,58,42,41,58,27,51,28,51,50,28,23,25,24,22,25,23,3,44,51,26,51,27,41,40,58,18,25,22,46,45,59,44,46,59,19,18,22,53,51,26,18,53,25,25,53,26,46,60,45,53,52,51,0,43,45,60,0,45,52,3,51,18,17,53,2,60,46,2,46,44,3,2,44,17,16,53,16,52,53,2,1,60,60,1,0,52,54,3,54,4,3,54,5,4,16,13,52,10,54,52,13,12,52,12,10,52,7,6,5,15,14,16,14,13,16,10,9,54,54,7,5,12,11,10,9,7,54,8,7,9],"type":"mesh","transform":{},"slotPose":[1,0,0,1,0,0],"userEdges":[],"width":64,"height":108,"name":"Layer 154","weights":[3,9,0.01117,14,0.34607,19,0.64277,3,14,0.14509,19,0.84458,22,0.01033,4,14,0.02879,19,0.84201,22,0.1285,25,0.0007,4,14,0.00032,19,0.23994,22,0.70444,25,0.0553,3,19,0.00683,22,0.75902,25,0.23415,3,19,0.00382,22,0.74858,25,0.2476,2,22,0.72135,25,0.27865,2,22,0.71349,25,0.28651,2,22,0.67692,25,0.32308,2,22,0.66479,25,0.33521,2,22,0.61772,25,0.38228,2,22,0.51888,25,0.48112,2,22,0.44611,25,0.55389,2,22,0.00827,25,0.99173,1,25,1,2,22,0.00001,25,0.99999,3,22,0.62516,25,0.35208,24,0.02276,2,22,0.52593,24,0.47407,2,22,0.20447,24,0.79553,1,24,1,1,24,1,1,24,1,1,24,1,1,24,1,2,22,0.00029,24,0.99971,3,19,0.00326,22,0.10568,24,0.89106,3,19,0.01506,22,0.31218,24,0.67276,3,19,0.05885,22,0.5054,24,0.43575,3,19,0.16752,22,0.58601,24,0.24647,3,19,0.54635,22,0.39297,24,0.06068,4,14,0.01239,19,0.78116,22,0.19112,24,0.01533,4,14,0.10242,19,0.8414,22,0.05453,24,0.00166,4,9,0.02497,14,0.49502,19,0.47958,22,0.00043,3,9,0.29468,14,0.60402,19,0.10131,3,9,0.71737,14,0.28254,19,0.00009,2,9,0.82089,14,0.17911,2,9,0.9174,14,0.0826,2,9,0.99485,14,0.00515,1,9,1,1,9,1,1,9,1,2,9,0.95961,14,0.04039,3,9,0.57165,14,0.36911,19,0.05924,3,9,0.11056,14,0.52316,19,0.36628,4,14,0.0134,19,0.89601,22,0.09017,25,0.00042,3,9,0.02205,14,0.4307,19,0.54725,3,14,0.09155,19,0.8958,22,0.01265,4,14,0.10969,19,0.88242,22,0.00782,24,0.00007,4,14,0.02751,19,0.9217,22,0.04799,24,0.0028,4,14,0.00142,19,0.63754,22,0.32437,24,0.03667,3,19,0.33636,22,0.62863,24,0.03501,2,22,0.98023,24,0.01977,2,22,0.85818,25,0.14182,2,22,0.41185,24,0.58815,3,19,0.00045,22,0.71954,25,0.28002,3,9,0.58608,14,0.39226,19,0.02167,3,9,0.05561,14,0.80627,19,0.13811,3,9,0.77679,14,0.22291,19,0.0003,2,9,0.99471,14,0.00529,2,14,0.00007,19,0.99993,3,14,0.1583,19,0.83427,22,0.00743,4,14,0.00998,19,0.75494,22,0.21462,24,0.02046]}],"name":"Layer 154"},{"display":[{"vertices":[-26.49,-91.68,-27.76,-88.85,-30.66,-88.12,-30.66,-84.83,-44.33,-79.68,-44.32,-70.89,-28.74,-55.65,-20.82,-58.82,-8.26,-55.12,4.68,-55.12,11.93,-64.9,18.33,-71.24,26.45,-73.54,31.46,-78.49,36.68,-85.69,36.67,-89.12,20.58,-89.12,13.05,-95.13,12.5,-98.12,7.16,-98.12,6.3,-95.76,3.73,-94.64,-1.22,-90.08,-6.63,-89.16,-11.65,-86.78,-14.82,-86.78,-20.49,-88.89,-21.35,-93.31,-30,-72.2,-11.38,-67.11,12.11,-78],"edges":[4,5,5,6,6,7,7,8,8,9,9,10,10,11,11,12,12,13,13,14,14,15,15,16,16,17,17,18,18,19,19,20,20,21,21,22,22,23,23,24,24,25,25,26,26,27,27,0,0,1,1,2,2,3,3,4],"path":"Layer 156","uvs":[0.22008,0.14964,0.2046,0.21564,0.16874,0.23253,0.16874,0.30927,0,0.42899,0.00008,0.63313,0.19237,0.98769,0.29015,0.91402,0.44517,1,0.60488,1,0.69451,0.77259,0.77354,0.62524,0.87377,0.57152,0.93569,0.4564,1,0.2891,1,0.20929,0.80125,0.20929,0.70836,0.06961,0.70162,0,0.63562,0,0.62503,0.05498,0.59325,0.08107,0.53214,0.18698,0.46533,0.20847,0.4034,0.26372,0.36429,0.26372,0.29422,0.21461,0.28362,0.11177,0.17688,0.60293,0.40666,0.72112,0.69674,0.46786],"bonePose":[15,-0.6640567179275978,0.7476822021254932,-0.7476822021254932,-0.6640567179275978,-19.96,-79.81,10,1,0,0,1,-9.76,-82.01,11,0.1911516362724023,0.9815605187406344,-0.9815605187406344,0.1911516362724023,-9.06,-80.51,16,0.9924394226563016,0.12273545680701482,-0.12273545680701482,0.9924394226563016,3.540000000000001,-87.75],"triangles":[16,13,14,16,14,15,16,12,13,16,30,12,30,11,12,17,30,16,30,10,11,19,20,17,17,20,30,20,21,30,21,22,30,30,29,10,19,17,18,22,29,30,29,9,10,24,29,23,23,29,22,29,8,9,25,29,24,29,7,8,25,28,29,26,28,25,28,7,29,3,28,26,28,6,7,1,3,26,0,1,26,0,26,27,28,5,6,2,3,1,4,28,3,4,5,28],"type":"mesh","transform":{},"slotPose":[1,0,0,1,0,0],"userEdges":[],"width":81,"height":43,"name":"Layer 156","weights":[2,15,0.939,10,0.061,2,15,0.96372,10,0.03628,2,15,0.98473,10,0.01527,2,15,0.99519,10,0.00481,1,15,1,1,15,1,2,11,0.079,15,0.921,2,11,0.35907,15,0.64093,2,11,0.96569,15,0.03431,2,16,0.05672,11,0.94328,2,16,0.36671,11,0.63329,2,16,0.76421,11,0.23579,2,16,0.95537,11,0.04463,2,16,0.99499,11,0.00501,1,16,1,1,16,1,1,16,1,1,16,1,1,16,1,1,16,1,1,16,1,2,16,0.99658,10,0.00342,3,16,0.75561,11,0.028,10,0.21639,4,16,0.29434,11,0.02276,15,0.00074,10,0.68217,3,16,0.03544,15,0.12815,10,0.83642,3,16,0.00145,15,0.40816,10,0.59038,2,15,0.84511,10,0.15489,2,15,0.91223,10,0.08777,1,15,1,2,11,0.84599,15,0.15401,2,16,0.78491,11,0.21509]}],"name":"Layer 156"},{"display":[{"path":"Layer 145","type":"image","name":"Layer 145","transform":{"y":3.74,"skX":-103.01,"skY":-103.01,"x":2.49}}],"name":"Layer 145"},{"display":[{"path":"Layer 7 copy","type":"image","name":"Layer 7 copy","transform":{"y":-0.6,"skX":-5.56,"skY":-5.56,"x":12.83}}],"name":"Layer 7 copy"},{"display":[{"path":"Layer 150","type":"image","name":"Layer 150","transform":{"y":-1.31,"skX":-119.05,"skY":-119.05,"x":15.34}}],"name":"Layer 150"},{"display":[{"path":"Layer 11 copy","type":"image","name":"Layer 11 copy","transform":{"y":-1.38,"skX":-71.43,"skY":-71.43,"x":15.27}}],"name":"Layer 11 copy"},{"display":[{"path":"Layer 148","type":"image","name":"Layer 148","transform":{"y":1.77,"skX":-66.02,"skY":-66.02,"x":3.18}}],"name":"Layer 148"},{"display":[{"path":"Layer 146","type":"image","name":"Layer 146","transform":{"y":3.31,"skX":-132.94,"skY":-132.94,"x":26.35}}],"name":"Layer 146"}],"name":""}]}],"name":"DaggerGoblin","version":"5.0"}